streamsbpy/__init__.py
streamsbpy/streamsbpy.py
streamsbpy-1.0.10.dist-info/LICENSE
streamsbpy-1.0.10.dist-info/METADATA
streamsbpy-1.0.10.dist-info/WHEEL
streamsbpy-1.0.10.dist-info/RECORD
