Metadata-Version: 2.1
Name: streamsbpy
Version: 1.0.10
Summary: Interact Using StreamSb API
Home-page: https://github.com/Code-xed
License: GNU General Public License 3.0
Author: Code-xed
Requires-Python: >=3.7,<4.0
Classifier: License :: Other/Proprietary License
Classifier: Programming Language :: Python :: 3
Classifier: Programming Language :: Python :: 3.7
Classifier: Programming Language :: Python :: 3.8
Classifier: Programming Language :: Python :: 3.9
Classifier: Programming Language :: Python :: 3.10
Classifier: Programming Language :: Python :: 3.11
Requires-Dist: requests (>=2.27.0,<3.0.0)
Project-URL: Repository, https://github.com/Code-xed
